kaggle_submissions/__init__.py
kaggle_submissions/transformations.py
kaggle_submissions-0.0.1.dist-info/licenses/LICENSE
kaggle_submissions-0.0.1.dist-info/WHEEL
kaggle_submissions-0.0.1.dist-info/METADATA
kaggle_submissions-0.0.1.dist-info/RECORD
