Metadata-Version: 2.4
Name: kaggle_submissions
Version: 0.0.1
Summary: A template Python module
Home-page: https://github.com/IslasGECI/kaggle
Author: Ciencia de Datos • GECI
Author-email: ciencia.datos@islas.org.mx
Requires-Python: >=3.9
Classifier: License :: OSI Approved :: GNU General Public License v3 or later (GPLv3+)
License-File: LICENSE
Requires-Dist: scikit-learn
Requires-Dist: numpy
Requires-Dist: pandas
